ngpuinfo/__init__.py
ngpuinfo/byte_units.py
ngpuinfo/ngpu.py
ngpuinfo/ngpu_detect.py
ngpuinfo/ngpuinfo.py
ngpuinfo/xml_parser.py
ngpuinfo-0.1.0.dist-info/LICENSE
ngpuinfo-0.1.0.dist-info/METADATA
ngpuinfo-0.1.0.dist-info/WHEEL
ngpuinfo-0.1.0.dist-info/top_level.txt
ngpuinfo-0.1.0.dist-info/RECORD
