Metadata-Version: 2.1
Name: ngpuinfo
Version: 0.1.0
Summary: A simple package used for getting gpu information.
Home-page: https://github.com/malanore-z//ngpuinfo
Author: malanore
Author-email: malanore.z@gmail.com
License: UNKNOWN
Project-URL: Bug Tracker, https://github.com/malanore-z//ngpuinfo/issues
Platform: UNKNOWN
Classifier: Programming Language :: Python :: 3
Classifier: License :: OSI Approved :: MIT License
Classifier: Operating System :: OS Independent
Requires-Python: >=3.4
